golos-0.2.3.dist-info/DESCRIPTION.rst
golos-0.2.3.dist-info/METADATA
golos-0.2.3.dist-info/RECORD
golos-0.2.3.dist-info/WHEEL
golos-0.2.3.dist-info/metadata.json
golos-0.2.3.dist-info/top_level.txt
golosapi/__init__.py
golosapi/golosasyncclient.py
golosapi/golosclient.py
golosapi/golosnoderpc.py
golosapi/goloswalletrpc.py
golosbase/__init__.py
golosbase/account.py
golosbase/chains.py
golosbase/memo.py
golosbase/objecttypes.py
golosbase/operations.py
golosbase/signedtransactions.py
golosbase/transactions.py
golosexchange/__init__.py
golosexchange/deep_eq.py
golosexchange/exchange.py
steemapi/__init__.py
steemapi/steemasyncclient.py
steemapi/steemclient.py
steemapi/steemnoderpc.py
steemapi/steemwalletrpc.py
steembase/__init__.py
steembase/account.py
steembase/chains.py
steembase/memo.py
steembase/objecttypes.py
steembase/operations.py
steembase/signedtransactions.py
steembase/transactions.py
steemexchange/__init__.py
steemexchange/deep_eq.py
steemexchange/exchange.py
